{
    "pages": {
      "1": {
        "text": "",
        "metadata": {
          "Setting": "",
          "Time": ""
        },
        "options": [
          {
            "text": "",
            "nextPage": "2"
          },
          {
            "text": "",
            "nextPage": "3"
          }
        ]
      },
      "2": {
        "text": "",
        "metadata": {
          "Setting": "",
          "Time": ""
        },
        "options": [
          {
            "text": "",
            "nextPage": "4"
          },
          {
            "text": "",
            "nextPage": "5"
          }
        ]
      },
      "3": {
        "text": "",
        "metadata": {
          "Setting": "",
          "Time": ""
        },
        "options": [
          {
            "text": "",
            "nextPage": "6"
          },
          {
            "text": "",
            "nextPage": "7"
          }
        ]
      }
    }
  }
  